cagou/VERSION
cagou/__init__.py
cagou/core/__init__.py
cagou/core/behaviors.py
cagou/core/cagou_main.py
cagou/core/cagou_widget.py
cagou/core/common.py
cagou/core/common_widgets.py
cagou/core/config.py
cagou/core/constants.py
cagou/core/dialog.py
cagou/core/image.py
cagou/core/kivy_hack.py
cagou/core/menu.py
cagou/core/patches.py
cagou/core/profile_manager.py
cagou/core/share_widget.py
cagou/core/simple_xhtml.py
cagou/core/widgets_handler.py
cagou/core/xmlui.py
cagou/core/platform_/__init__.py
cagou/core/platform_/android.py
cagou/core/platform_/base.py
cagou/kv/__init__.py
cagou/kv/base.kv
cagou/kv/behaviors.kv
cagou/kv/cagou_widget.kv
cagou/kv/common.kv
cagou/kv/common_widgets.kv
cagou/kv/dialog.kv
cagou/kv/menu.kv
cagou/kv/profile_manager.kv
cagou/kv/root_widget.kv
cagou/kv/share_widget.kv
cagou/kv/simple_xhtml.kv
cagou/kv/widgets_handler.kv
cagou/kv/xmlui.kv
cagou/plugins/__init__.py
cagou/plugins/plugin_transfer_android_gallery.py
cagou/plugins/plugin_transfer_android_photo.py
cagou/plugins/plugin_transfer_android_video.py
cagou/plugins/plugin_transfer_file.kv
cagou/plugins/plugin_transfer_file.py
cagou/plugins/plugin_transfer_voice.kv
cagou/plugins/plugin_transfer_voice.py
cagou/plugins/plugin_wid_chat.kv
cagou/plugins/plugin_wid_chat.py
cagou/plugins/plugin_wid_contact_list.kv
cagou/plugins/plugin_wid_contact_list.py
cagou/plugins/plugin_wid_file_sharing.kv
cagou/plugins/plugin_wid_file_sharing.py
cagou/plugins/plugin_wid_remote.kv
cagou/plugins/plugin_wid_remote.py
cagou/plugins/plugin_wid_settings.kv
cagou/plugins/plugin_wid_settings.py
cagou/plugins/plugin_wid_widget_selector.kv
cagou/plugins/plugin_wid_widget_selector.py
libervia_desktop-0.8.0.dist-info/COPYING
libervia_desktop-0.8.0.dist-info/METADATA
libervia_desktop-0.8.0.dist-info/WHEEL
libervia_desktop-0.8.0.dist-info/entry_points.txt
libervia_desktop-0.8.0.dist-info/top_level.txt
libervia_desktop-0.8.0.dist-info/RECORD
