Metadata-Version: 2.1
Name: libervia-desktop
Version: 0.8.0
Summary: Desktop/Android frontend for Libervia XMPP client
Home-page: https://salut-a-toi.org
Author: Association « Salut à Toi »
Author-email: contact@goffi.org
License: UNKNOWN
Platform: UNKNOWN
Classifier: Programming Language :: Python :: 3 :: Only
Classifier: Programming Language :: Python :: 3.7
Classifier: Programming Language :: Python :: 3.8
Classifier: Programming Language :: Python :: 3.9
Classifier: Development Status :: 5 - Production/Stable
Classifier: Environment :: X11 Applications
Classifier: Framework :: Twisted
Classifier: License :: OSI Approved :: GNU Affero General Public License v3 or later (AGPLv3+)
Classifier: Operating System :: POSIX :: Linux
Classifier: Operating System :: Android
Classifier: Topic :: Internet :: XMPP
Classifier: Topic :: Communications :: Chat
Classifier: Intended Audience :: End Users/Desktop
Requires-Python: >=3.7
License-File: COPYING
Requires-Dist: kivy (<2.1.0,>=2.0.0)
Requires-Dist: kivy-garden.modernmenu
Requires-Dist: pillow (<8.3)
Requires-Dist: plyer (<2.1)
Requires-Dist: libervia-backend (<0.9,>=0.8.0b1)
